minwell/.DS_Store
minwell/__init__.py
minwell/minwell.py
minwell/setup.py
minwell/theory/.DS_Store
minwell/theory/100_1.jpg
minwell/theory/101_1.jpg
minwell/theory/102_1.jpg
minwell/theory/103_1.jpg
minwell/theory/104_1.jpg
minwell/theory/104_2.jpg
minwell/theory/105_1.jpg
minwell/theory/106_1.jpg
minwell/theory/106_2.jpg
minwell/theory/107_1.jpg
minwell/theory/107_2.jpg
minwell/theory/108_1.jpg
minwell/theory/109_1.jpg
minwell/theory/10_1.png
minwell/theory/10_2.png
minwell/theory/10_3.png
minwell/theory/110_1.jpg
minwell/theory/111_1.jpg
minwell/theory/111_2.jpg
minwell/theory/112_1.jpg
minwell/theory/113_1.jpg
minwell/theory/114_1.jpg
minwell/theory/114_2.jpg
minwell/theory/115_1.jpg
minwell/theory/115_2.jpg
minwell/theory/116_1.jpg
minwell/theory/117_1.jpg
minwell/theory/118_1.jpg
minwell/theory/119_1.jpg
minwell/theory/11_1.png
minwell/theory/120_1.jpg
minwell/theory/120_2.jpg
minwell/theory/121_1.jpg
minwell/theory/12_1.png
minwell/theory/13_1.png
minwell/theory/13_2.png
minwell/theory/14_1.png
minwell/theory/15_1.png
minwell/theory/15_2.png
minwell/theory/16_1.png
minwell/theory/17_1.png
minwell/theory/18_1.png
minwell/theory/19_1.png
minwell/theory/1_1.png
minwell/theory/1_2.png
minwell/theory/20_1.png
minwell/theory/20_2.png
minwell/theory/21_1.png
minwell/theory/22_1.png
minwell/theory/22_2.png
minwell/theory/23_1.png
minwell/theory/24_1.png
minwell/theory/24_2.png
minwell/theory/24_3.png
minwell/theory/25_1.png
minwell/theory/25_2.png
minwell/theory/26_1.png
minwell/theory/27_1.png
minwell/theory/28_1.png
minwell/theory/29_1.png
minwell/theory/2_1.png
minwell/theory/30_1.png
minwell/theory/30_2.png
minwell/theory/31_1.png
minwell/theory/31_2.png
minwell/theory/32_1.png
minwell/theory/33_1.png
minwell/theory/34_1.png
minwell/theory/35_1.png
minwell/theory/36_1.png
minwell/theory/36_2.png
minwell/theory/36_3.png
minwell/theory/37_1.png
minwell/theory/37_2.png
minwell/theory/38_1.png
minwell/theory/39_1.png
minwell/theory/39_2.png
minwell/theory/3_1.png
minwell-0.1.15.dist-info/METADATA
minwell-0.1.15.dist-info/WHEEL
minwell-0.1.15.dist-info/RECORD
